[
{"ID": 1293514372630708335, "Timestamp": "2024-10-09 10:04:18", "Contents": "Hola Xavier,ya os he enviado correo. Me confirmáis horario dentro de las franjas que os doy.", "Attachments": ""},
{"ID": 1288796297247068302, "Timestamp": "2024-09-26 09:36:21", "Contents": "Y la piedra que va alrededor", "Attachments": ""},
{"ID": 1288749899911004170, "Timestamp": "2024-09-26 06:31:59", "Contents": "Si,me refiero a pintar el tejado", "Attachments": ""},
{"ID": 1288202783224365076, "Timestamp": "2024-09-24 18:17:57", "Contents": "que tú ya cumpliste tu parte", "Attachments": ""},
{"ID": 1288202753792938045, "Timestamp": "2024-09-24 18:17:50", "Contents": "Solo si tienes chance, sino tranqui", "Attachments": ""},
{"ID": 1288202706384851117, "Timestamp": "2024-09-24 18:17:38", "Contents": "Y si quieres ayudarme, pues si tienes un rato, te digo para que me acabes tu casita esquinera con tejado, pero en version beige. Ahora estoy texturizando yo todo lo que hay y en cuanto empiecen clases ya me voy a atrasar.", "Attachments": ""},
{"ID": 1288202469976834089, "Timestamp": "2024-09-24 18:16:42", "Contents": "Listo, yo te informo del máster, ya van a enviarlo al Ces, yo estoy cerrando profes y creo que puede estar bueno. Poco antes que salga yo te cuento detalles.", "Attachments": ""},
{"ID": 1286749925534859285, "Timestamp": "2024-09-20 18:04:48", "Contents": "Hola! enhorabuena. Pues está bien que tengas trabajo entonces ☺️ eso primero", "Attachments": ""},
{"ID": 1286732735364202517, "Timestamp": "2024-09-20 16:56:30", "Contents": "<@321751055077605386>", "Attachments": ""},
{"ID": 1286069285927649291, "Timestamp": "2024-09-18 21:00:11", "Contents": "Pues si te ves con animo y tiempo,la verdad que a mí me gustaría pero también tendrías más carga teorica. Por favor,metete al Mooc y si me confirmas ahorita yo muevo todo para que seas mi ayudante,pero de ley necesito que estés en ese Mooc sino no me dejarán.", "Attachments": ""},
{"ID": 1286026589129150495, "Timestamp": "2024-09-18 18:10:32", "Contents": "Eso sí tendríamos que escribir algo,pero creo nos lo sacamos y ahora están sacando un tema que son medallas de investigación por publicaciones o una vaina así,no es plata pero bueno. Porque por itinerario plata no hay. Es lo único que puedo ofrecerte,pero si vas a tener el tiempo junto a integradora.", "Attachments": ""},
{"ID": 1286026298313146510, "Timestamp": "2024-09-18 18:09:22", "Contents": "Y de ahí soy yo la que muevo los papeles", "Attachments": ""},
{"ID": 1286026259033489480, "Timestamp": "2024-09-18 18:09:13", "Contents": "Tienes que registrarte en el Mooc de investigación creo que hasta mañana", "Attachments": ""},
{"ID": 1286026060252581889, "Timestamp": "2024-09-18 18:08:25", "Contents": "Porque la verdad con textura hiciste trabajo buenísimo. Algo podemos seguir avanzando", "Attachments": ""},
{"ID": 1286025611231625216, "Timestamp": "2024-09-18 18:06:38", "Contents": "Y de repente ahí vemos cositas de Z y me sigues ayudando.", "Attachments": ""},
{"ID": 1286025481438761022, "Timestamp": "2024-09-18 18:06:07", "Contents": "Plata porque eso es Espol,no yo.", "Attachments": ""},
{"ID": 1286025479186419807, "Timestamp": "2024-09-18 18:06:07", "Contents": "Claro que no te puedo garantizar plaza", "Attachments": ""},
{"ID": 1286025366418358384, "Timestamp": "2024-09-18 18:05:40", "Contents": "Oye Xavier y cómo estarás de tiempo este término? Porque estoy pensando igual puedes seri ayudante de investigación,me.he informado y si hay plata algo te pagan de Espol pero no es seguro", "Attachments": ""},
{"ID": 1286025073769185425, "Timestamp": "2024-09-18 18:04:30", "Contents": "Los cursos esos depende,la mayoría son malos o para gente que ya sepa porque dan cosas súper específicas o desordenadas. Odin es súper pro y empieza desde cero,ya voy a buscar bien si hay algo en abierto. Lo que hay Crehana meh.", "Attachments": ""},
{"ID": 1285869383691927562, "Timestamp": "2024-09-18 07:45:51", "Contents": "Nosotros sacaremos una maestría toda de 3D y hay becas,te puedo avisar de cómo va sin compromiso. Por ahora estoy armando profes y es gente pepa que conozco que trabaja en industria. Sino,te puedo orientar de formación que conozco,pero ya en España.", "Attachments": ""},
{"ID": 1285868877406015561, "Timestamp": "2024-09-18 07:43:50", "Contents": "Y suele tener oferta,digo por si mientras estás con integradora de repente quieres ponerte con algo y ya después ves,quizás hacer una maestría para actualizarte y profundizar.", "Attachments": ""},
{"ID": 1285868576804180021, "Timestamp": "2024-09-18 07:42:38", "Contents": "Hay un chico que tiene sus cursos en línea que se llama Odin que es buenísimo en Zbrush y explica súper bien.", "Attachments": ""},
{"ID": 1285868415633985639, "Timestamp": "2024-09-18 07:42:00", "Contents": "Pero para especializarte en modelado 3D te van a pedir también Zbrush además de Substance y Maya o Max.", "Attachments": ""},
{"ID": 1285868001958170657, "Timestamp": "2024-09-18 07:40:21", "Contents": "También si puedes meterte a algún proyecto para no perder práctica.", "Attachments": ""},
{"ID": 1285867895808721027, "Timestamp": "2024-09-18 07:39:56", "Contents": "Ya,entonces integradora te va a tomar todo tu tiempo. Pues para modelado 3D te diría de armar un portfolio y de ahí seguir formandote", "Attachments": ""},
{"ID": 1285180891299057725, "Timestamp": "2024-09-16 10:10:01", "Contents": "Me gustaría mucho que me siguieses ayudando, pero Itinerario creo que al exigir más investigación, no podríamos avanzar mucho a nivel práctico.", "Attachments": ""},
{"ID": 1285179970620231776, "Timestamp": "2024-09-16 10:06:22", "Contents": "Por otro lado, tus horas de preprofesioanles las tienes hechas¿?", "Attachments": ""},
{"ID": 1285179882438918164, "Timestamp": "2024-09-16 10:06:01", "Contents": "Hola Xavier, disculpa que no te contesté a tiempo. Modelado 3D y VFX son cosas diferentes y por tanto, dos especialidades. Deberías, primeramente saber qué es lo que te interesa más y de ahí, yo si fuese tú armaría un pequeño dossier para aplicar a prácticas y de ahí, probablemente hacer una maestría. Dime qué es lo que más te interesa y de ahí te puedo echar la mano.", "Attachments": ""},
{"ID": 1268446941017280533, "Timestamp": "2024-08-01 05:55:17", "Contents": "Hola Xavier,tus modelos se ven perfectamente en Unreal. Es probable que en Cinema los archivos aparezcan más triangulados o con problemas de topología. Pero lo que yo he comprobado en Unreal está ok. Lo que me falta es el mueble aparador.", "Attachments": ""}
]