[
{"ID": 1405588773080924200, "Timestamp": "2025-08-14 16:27:58", "Contents": "@everyone indicadme, porfa , quién ha marcado una mesa en el set de rodaje con una cartulina amarilla. Necesito saber si ha quedado de trabajos anteriores o cuándo se va a usar, para poder contar con ella.", "Attachments": ""},
{"ID": 1296138379922112593, "Timestamp": "2024-10-16 15:51:10", "Contents": "@everyone del semestre pasado, en el MOTION LAB  ha quedado un candado en el casillero 9. Es de alguno de vosotros?sino, lo romperemos para usar ese casillero.", "Attachments": ""},
{"ID": 1262833946803310755, "Timestamp": "2024-07-16 18:11:15", "Contents": "@everyone 🎮 La Facultad de Arte, Diseño y Comunicación Audiovisual de la ESPOL invita al evento \"Las mujeres y los videojuegos: jugadoras, desarrolladoras y protagonistas\". \n\n🚺 Junto a destacadas expertas en el campo, exploraremos la participación de las mujeres en el desarrollo y diseño de videojuegos, los desafíos y oportunidades que enfrentan en esta industria y el impacto de los videojuegos en la construcción de la identidad femenina. 🌟\n\n📅 Fecha: Miércoles 17 de julio del 2024\n🕙 Hora: 10:00\n📍 Lugar: Auditorios FADCOM (Edificio 14B, Campus Gustavo Galindo, Km 30.5 Vía Perimetral) \n\nModalidad Híbrida:\nZoom: https://cedia.zoom.us/j/84906908704\n\n#MujeresEnVideojuegos #FADCOM #EventoAcademico #Guayaquil #Ecuador\nZoom Video\nJoin our Cloud HD Video Meeting\nZoom is the leader in modern enterprise video communications, with an easy, reliable cloud platform for video and audio conferencing, chat, and webinars across mobile, desktop, and room systems. Zoom Rooms is the original software-based conference room solution used around the world in board, conference, huddle, and training rooms, as well as ex...", "Attachments": ""},
{"ID": 1209431216860823623, "Timestamp": "2024-02-20 09:27:52", "Contents": "Vale,genial, gracias 😊", "Attachments": ""},
{"ID": 1204877446650794004, "Timestamp": "2024-02-07 19:52:48", "Contents": "Dale,pues ya notifico entonces. Gracias 😊", "Attachments": ""},
{"ID": 1204872639139680286, "Timestamp": "2024-02-07 19:33:42", "Contents": "Dale,eso dije. Sabemos algo de la otra llave?", "Attachments": ""},
{"ID": 1204823006556463195, "Timestamp": "2024-02-07 16:16:29", "Contents": "Mmm yo creo que sí doy tu nombre se desesperarán menos y digo que después de Carnavales?", "Attachments": ""},
{"ID": 1204818485839138836, "Timestamp": "2024-02-07 15:58:31", "Contents": "Okis y tienes manera de hacerla llegar a Fadcom? Si no puedes tú,que alguien la lleve por ti?", "Attachments": ""},
{"ID": 1204807402013073459, "Timestamp": "2024-02-07 15:14:28", "Contents": "@everyone los y las que usaron los casilleros,por favor me indican. Deben entregar las llaves y me están reclamando que faltan dos. Porfa díganme algo.", "Attachments": ""},
{"ID": 1204453370665111563, "Timestamp": "2024-02-06 15:47:41", "Contents": "https://www.instagram.com/p/C3AZiTINqjR/?igsh=ZmtkOTU2a2Foa3Jv @everyone", "Attachments": ""},
{"ID": 1196204007794933801, "Timestamp": "2024-01-14 21:27:39", "Contents": "@everyone disculpad que moleste en domingo,pero tengo novedades respecto al acceso al aula. Todas y todas las que tengan que ir a recoger sus cosas para continuar con su proyecto final en la casa,por favor me comunican por privado.", "Attachments": ""},
{"ID": 1187068507184189552, "Timestamp": "2023-12-20 16:26:26", "Contents": "@everyone probando con una compañera, la versión 4 de Dragon que tenemos compartida en la carpeta, funciona bien con cámara Sony, por si es de ayuda. Por acá dejo la carpeta compartida: https://espolec-my.sharepoint.com/:f:/g/personal/ircabrer_espol_edu_ec/EhJMeoI-l-dNlprT8uhNVvcB-ir4zL1yxSrLY5dFc4A10A?e=5JLjjS", "Attachments": ""},
{"ID": 1181646465077100544, "Timestamp": "2023-12-05 17:21:11", "Contents": "https://www.artistapirata.com/?s=Drag%C3%B3n+frame", "Attachments": ""},
{"ID": 1164466810196869160, "Timestamp": "2023-10-19 07:35:22", "Contents": "https://www.instagram.com/p/CyioMV4y_7N/?igshid=YTUzYTFiZDMwYg==. @everyone", "Attachments": ""},
{"ID": 1138526063849373796, "Timestamp": "2023-08-08 17:36:06", "Contents": "La animatica no es la animación final. Estoy segura que el profesor Cantos os explicará muy bien qué es,es lo que os toca hoy día.", "Attachments": ""},
{"ID": 1135995445932478554, "Timestamp": "2023-08-01 18:00:20", "Contents": "Cada grupo tiene su idea,su técnica,pero cada uno se centra en su parte. Cada uno hace su minuto y se centra en eso. Si cada uno parte de una cosa diferente entonces son películas diferentes. IMAGINA Que estás haciendo una PELÍCULA y a ti te toca una parte.   @everyone", "Attachments": ""},
{"ID": 1135994568857354491, "Timestamp": "2023-08-01 17:56:50", "Contents": "Vamos a ver, el tema es GRUPAL,cada uno hace su parte.", "Attachments": ""},
{"ID": 1135993010207870976, "Timestamp": "2023-08-01 17:50:39", "Contents": "Cuando ese trabajo este aprobado y ok, entonces,os enviaré a unir el animatic", "Attachments": ""},
{"ID": 1135992915374649344, "Timestamp": "2023-08-01 17:50:16", "Contents": "Cada uno su animatic", "Attachments": ""},
{"ID": 1135992892742172703, "Timestamp": "2023-08-01 17:50:11", "Contents": "Cada uno su storyboard", "Attachments": ""},
{"ID": 1135992123628466226, "Timestamp": "2023-08-01 17:47:07", "Contents": "Lo único es que al final vais a montar el vídeo en común y en el pitch lo presentareis acabado en conjunto al final.", "Attachments": ""},
{"ID": 1135991908628435075, "Timestamp": "2023-08-01 17:46:16", "Contents": "Cada uno su parte y a su carpeta personal. Cada uno anima una parte,cada uno tiene su nota,cada uno presenta su parte aunque estéis trabajando en algo común. Imaginate que estás trabajando en un estudio de animación, TODOS hacen una película pero cada uno,una parte. Pues LO MISMO.   @everyone", "Attachments": ""},
{"ID": 1118183369566597203, "Timestamp": "2023-06-13 14:21:30", "Contents": "IMG-20230608-WA0028.jpg\n \n\nLINK DE REGISTRO:\n\nhttps://forms.office.com/Pages/ResponsePage.aspx?id=r4yvt9iDREaFrjF8VFIjwfQUXWO_HaBBmJijn9kUeq1URTlWVkRIUFlEMjVHWExYN0tWME5GVVJBVC4u (Enlaces a un sitio externo.)", "Attachments": ""},
{"ID": 1117974085679464509, "Timestamp": "2023-06-13 00:29:52", "Contents": "@everyone si les interesa es mañana vía Zoom", "Attachments": "https://cdn.discordapp.com/attachments/897515396708565005/1117974085356494899/IMG-20230608-WA0028.jpg?ex=0&is=68b7009b&hm=04abd8fc5fb5c6b5c1b0746f5dede2e26b6160b309927f6e47d241a21e992631&uc=dp&"},
{"ID": 1103690111952097302, "Timestamp": "2023-05-04 14:30:28", "Contents": "@everyone estoy buscando personas de concept para abrir un itinerario. Si existen personas interesadas que me escriban a más tardar hasta mañana a las 10:00 a mi mail y me envían muestras de trabajo.", "Attachments": ""},
{"ID": 1072620685593149601, "Timestamp": "2023-02-07 20:51:39", "Contents": "@everyone por si les interesa hay un Jam este fin de semana en Gye. Noes solamente de modelado o desarrollo, también si hacen ilustración pueden aplicar : https://openlab.ec/ggjgye-2023#no-back", "Attachments": ""},
{"ID": 1067542814847668326, "Timestamp": "2023-01-24 20:34:01", "Contents": "Si sois de Uartes os agradezco compartáis también en vuestra U", "Attachments": ""},
{"ID": 1067542710786986074, "Timestamp": "2023-01-24 20:33:36", "Contents": "https://docs.google.com/forms/d/e/1FAIpQLSe4TxQPmqVPGxaYedtzah1_Qo_elqt9JJWx0eoh4ZK1waOUCQ/viewform?vc=0&c=0&w=1&flr=0", "Attachments": ""},
{"ID": 1067542602011906089, "Timestamp": "2023-01-24 20:33:10", "Contents": "@everyone me podríais ayudar completando una encuesta sobre un posgrado que estoy proponiendo en Espol?", "Attachments": ""},
{"ID": 1044190100550066177, "Timestamp": "2022-11-21 09:58:40", "Contents": "", "Attachments": "https://cdn.discordapp.com/attachments/897515396708565005/1044190100164194374/image.png?ex=0&is=68b70259&hm=5217c2889a2d9ea3882678526abdf8cad48f416599355df25a3cf888189b78a1&uc=dp&"},
{"ID": 1044190002566934548, "Timestamp": "2022-11-21 09:58:16", "Contents": "", "Attachments": "https://cdn.discordapp.com/attachments/897515396708565005/1044190002239770694/image.png?ex=0&is=68b70259&hm=43ab6ece5578725b8435d482484127b3e28257c9f82bad2c4778bc0b52d52d55&uc=dp&"},
{"ID": 1044181409482416168, "Timestamp": "2022-11-21 09:24:07", "Contents": "Hola,no he metido ningún código en eso, desconozco porqué lo pide. Yo he accedido como estudiante y puedo ver todo sin problema. Debéis haceros una cuenta en EdPuzzle, pero dáis click en mostrar-hacéis click en el video y ya sale la actividad. ¿Habéis conseguido resolverlo?", "Attachments": ""},
{"ID": 1032758912753074187, "Timestamp": "2022-10-20 20:55:12", "Contents": "@everyone Buenas tardes,\n\nHoy día no podré dar la clase por el motivo de que me encuentro mal de salud, disculpad. Espero que si estáis en la universidad podáis tomar el bus de las 16:30 para poder regresar a casa. No os preocupéis, recuperaremos estas horas, ya sea síncronamente o asíncronamente. Por favor, avisad a vuestros compañeros y compañeras si acaso algunos estáis juntos.\n\n \n\nDisculpad de nuevo.\n\nSaludos.", "Attachments": ""},
{"ID": 1029515144113434624, "Timestamp": "2022-10-11 22:05:37", "Contents": "https://festivaledoc.org/", "Attachments": ""},
{"ID": 1029515007056162846, "Timestamp": "2022-10-11 22:05:05", "Contents": "@everyone", "Attachments": ""},
{"ID": 1029514963800313886, "Timestamp": "2022-10-11 22:04:54", "Contents": "", "Attachments": "https://cdn.discordapp.com/attachments/897515396708565005/1029514963557036082/agenda_de_actividades.jpeg?ex=0&is=68b70281&hm=03cb083d92bcbc51a3027364874a59eaa621fda138dd62e348473d97f0b8939c&uc=dp&"},
{"ID": 1029514940098281543, "Timestamp": "2022-10-11 22:04:49", "Contents": "", "Attachments": "https://cdn.discordapp.com/attachments/897515396708565005/1029514939909537902/thumbnail_invitacion_cortos_infantiles.jpg?ex=0&is=68b70281&hm=8d8aac694773b4d8f2044f176c8c00a12b3de3df03e1b2bd2f409749074fc2e4&uc=dp&"},
{"ID": 980964271435444224, "Timestamp": "2022-05-30 22:41:47", "Contents": "@everyone mañana haremos taller presencial para quien quiera asistir en la A104 que tiene mesas hexagonales. Traigan papel y lápiz.", "Attachments": ""}
]